biovars/Logger.py
biovars/Plotter.py
biovars/Search.py
biovars/Sources.py
biovars/__init__.py
biovars/cli.py
biovars/R_plotting_scripts/.DS_Store
biovars/R_plotting_scripts/plot_summary.r
biovars/R_plotting_scripts/region_plot.r
biovars/R_plotting_scripts/world_plot.r
biovars/R_plotting_scripts/assets/biovars_interactive.Rmd
biovars/R_plotting_scripts/assets/world_map.png
biovars-0.2.0.dist-info/LICENSE
biovars-0.2.0.dist-info/METADATA
biovars-0.2.0.dist-info/WHEEL
biovars-0.2.0.dist-info/entry_points.txt
biovars-0.2.0.dist-info/top_level.txt
biovars-0.2.0.dist-info/RECORD
