Metadata-Version: 2.1
Name: biovars
Version: 0.2.0
Summary: Tool for joining all the bioinfo-hcpa's variant information retrieval APIs.
Author: Felipe Colombelli
Author-email: Paola Carneiro <bioinfo@hcpa.edu.br>
License: GNU GENERAL PUBLIC LICENSE
Project-URL: Homepage, https://github.com/bioinfo-hcpa/biovars
Keywords: gnomad,api,variants,genes
Classifier: Intended Audience :: Developers
Classifier: Topic :: Software Development :: Build Tools
Classifier: License :: OSI Approved :: GNU General Public License v3 (GPLv3)
Classifier: Programming Language :: Python :: 3.8
License-File: LICENSE
Requires-Dist: pandas >=1.0.5
Requires-Dist: numpy ==1.23.3
Requires-Dist: requests >=2.24.0
Requires-Dist: pynoma
Requires-Dist: pyabraom
Provides-Extra: plots
Requires-Dist: rpy2 ==3.5.12 ; extra == 'plots'
Requires-Dist: seaborn ; extra == 'plots'
